README.md
setup.py
nmj_analyzer/Processing.py
nmj_analyzer/__init__.py
nmj_analyzer/__main__.py
nmj_analyzer/nmj_analyzer.py
nmj_analyzer/utils/__init__.py
nmj_analyzer/utils/morphology.py
nmj_analyzer/utils/pairwise_measures.py
nmjanalyzer.egg-info/PKG-INFO
nmjanalyzer.egg-info/SOURCES.txt
nmjanalyzer.egg-info/dependency_links.txt
nmjanalyzer.egg-info/entry_points.txt
nmjanalyzer.egg-info/top_level.txt