Metadata-Version: 2.1
Name: nmjanalyzer
Version: 0.0.3
Summary: NMJ Analyzer
Home-page: https://github.com/csudre/NMJ_Analyser
Author: Carole Sudre
Author-email: c.sudre@ucl.ac.uk
License: UNKNOWN
Platform: UNKNOWN
Classifier: Programming Language :: Python :: 3
Classifier: License :: OSI Approved :: Apache Software License
Classifier: Operating System :: OS Independent
Requires-Python: >=3.6
